lex2sent/Bootstrap.py
lex2sent/__init__.py
lex2sent/textClass.py
lex2sent/tests/__init__.py
lex2sent/tests/test_RatedTexts.py
lex2sent-0.0.2.dist-info/LICENSE
lex2sent-0.0.2.dist-info/METADATA
lex2sent-0.0.2.dist-info/WHEEL
lex2sent-0.0.2.dist-info/top_level.txt
lex2sent-0.0.2.dist-info/RECORD
