Metadata-Version: 2.1
Name: lex2sent
Version: 0.0.2
Summary: A Python package to perform unsupervised sentiment analysis using lexicon enhanced Document embeddings
Home-page: https://github.com/K-RLange/Lex2Sent
Author: Kai-Robin Lange
Author-email: <kai-robin.lange@tu-dortmund.de>
License: UNKNOWN
Keywords: python,sentiment analysis,nlp,doc2vec,bagging,text classification
Platform: UNKNOWN
Classifier: Development Status :: 4 - Beta
Classifier: Intended Audience :: End Users/Desktop
Classifier: Intended Audience :: Developers
Classifier: Programming Language :: Python :: 3
Classifier: Operating System :: Unix
Classifier: Operating System :: MacOS :: MacOS X
Classifier: Operating System :: Microsoft :: Windows
License-File: LICENSE
Requires-Dist: nltk
Requires-Dist: gensim
Requires-Dist: pandas
Requires-Dist: vaderSentiment
Requires-Dist: scipy
Requires-Dist: numpy
Requires-Dist: tqdm
